popeye/__init__.py
popeye/auditory.py
popeye/auditory_hrf.py
popeye/auditory_stimulus.py
popeye/base.py
popeye/css.py
popeye/css_regularized.py
popeye/dog.py
popeye/gabor.py
popeye/og.py
popeye/og_hrf.py
popeye/og_regularized_hrf.py
popeye/onetime.py
popeye/plotting.py
popeye/reconstruction.py
popeye/simulation.py
popeye/spatiotemporal.py
popeye/spatiotemporal_2dcos.py
popeye/spatiotemporal_css.py
popeye/spatiotemporal_hrf.py
popeye/spectrotemporal.py
popeye/spinach.cpython-36m-darwin.so
popeye/utilities.py
popeye/version.py
popeye/visual_stimulus.py
popeye/xvalidation.py
popeye/tests/test_auditory.py
popeye/tests/test_auditory_hrf.py
popeye/tests/test_base.py
popeye/tests/test_css.py
popeye/tests/test_dog.py
popeye/tests/test_og.py
popeye/tests/test_og_hrf.py
popeye/tests/test_spatiotemporal.py
popeye/tests/test_spatiotemporal_2dcos.py
popeye/tests/test_spatiotemporal_css.py
popeye/tests/test_spatiotemporal_hrf.py
popeye/tests/test_spinach.py
popeye/tests/test_stimulus.py
popeye/tests/test_strf.py
popeye/tests/test_utilities.py
popeye/tests/test_xvalidation.py
popeye-1.0.0.dist-info/LICENSE
popeye-1.0.0.dist-info/METADATA
popeye-1.0.0.dist-info/WHEEL
popeye-1.0.0.dist-info/top_level.txt
popeye-1.0.0.dist-info/RECORD
