Metadata-Version: 2.1
Name: popeye
Version: 1.0.0
Summary: popeye : voxel population receptive fields from fMRI data
Home-page: https://github.com/kdesimone/popeye/
Author: Kevin Desimone
Author-email: kevindesimone@gmail.com
Maintainer: Kevin DeSimone
Maintainer-email: kevindesimone@gmail.com
License: Simplified BSD
Download-URL: http://github.com/kdesimone/popeye/downloads
Platform: OS Independent
Classifier: Development Status :: 3 - Alpha
Classifier: Environment :: Console
Classifier: Intended Audience :: Science/Research
Classifier: License :: OSI Approved :: BSD License
Classifier: Operating System :: OS Independent
Classifier: Programming Language :: Python
Classifier: Topic :: Scientific/Engineering
Requires-Dist: scipy
Requires-Dist: numpy
Requires-Dist: matplotlib
Requires-Dist: nibabel
Requires-Dist: statsmodels
Requires-Dist: sharedmem
Requires-Dist: cython
Requires-Dist: numexpr
